[{"day":"2020-09-05","locks":1185,"cumulative_locks":1185},{"day":"2020-09-06","locks":489,"cumulative_locks":1674},{"day":"2020-09-07","locks":782,"cumulative_locks":2456},{"day":"2020-09-08","locks":537,"cumulative_locks":2993},{"day":"2020-09-09","locks":769,"cumulative_locks":3762},{"day":"2020-09-10","locks":698,"cumulative_locks":4460},{"day":"2020-09-11","locks":455,"cumulative_locks":4915},{"day":"2020-09-12","locks":375,"cumulative_locks":5290},{"day":"2020-09-13","locks":352,"cumulative_locks":5642},{"day":"2020-09-14","locks":207,"cumulative_locks":5849},{"day":"2020-09-15","locks":238,"cumulative_locks":6087},{"day":"2020-09-16","locks":141,"cumulative_locks":6228},{"day":"2020-09-17","locks":21,"cumulative_locks":6249},{"day":"2020-09-18","locks":62,"cumulative_locks":6311},{"day":"2020-09-19","locks":8,"cumulative_locks":6319},{"day":"2020-09-20","locks":7,"cumulative_locks":6326},{"day":"2020-09-21","locks":12,"cumulative_locks":6338},{"day":"2020-09-22","locks":22,"cumulative_locks":6360},{"day":"2020-09-23","locks":23,"cumulative_locks":6383},{"day":"2020-09-24","locks":9,"cumulative_locks":6392},{"day":"2020-09-25","locks":18,"cumulative_locks":6410},{"day":"2020-09-26","locks":20,"cumulative_locks":6430},{"day":"2020-09-27","locks":13,"cumulative_locks":6443},{"day":"2020-09-28","locks":3,"cumulative_locks":6446},{"day":"2020-09-29","locks":13,"cumulative_locks":6459},{"day":"2020-09-30","locks":17,"cumulative_locks":6476},{"day":"2020-10-01","locks":13,"cumulative_locks":6489},{"day":"2020-10-02","locks":6,"cumulative_locks":6495},{"day":"2020-10-03","locks":3,"cumulative_locks":6498},{"day":"2020-10-04","locks":7,"cumulative_locks":6505},{"day":"2020-10-05","locks":14,"cumulative_locks":6519},{"day":"2020-10-06","locks":6,"cumulative_locks":6525},{"day":"2020-10-07","locks":3,"cumulative_locks":6528},{"day":"2020-10-08","locks":4,"cumulative_locks":6532},{"day":"2020-10-09","locks":3,"cumulative_locks":6535},{"day":"2020-10-10","locks":2,"cumulative_locks":6537},{"day":"2020-10-11","locks":12,"cumulative_locks":6549},{"day":"2020-10-12","locks":4,"cumulative_locks":6553},{"day":"2020-10-13","locks":8,"cumulative_locks":6561},{"day":"2020-10-14","locks":8,"cumulative_locks":6569},{"day":"2020-10-15","locks":6,"cumulative_locks":6575},{"day":"2020-10-16","locks":5,"cumulative_locks":6580},{"day":"2020-10-17","locks":8,"cumulative_locks":6588},{"day":"2020-10-18","locks":6,"cumulative_locks":6594},{"day":"2020-10-19","locks":2,"cumulative_locks":6596},{"day":"2020-10-20","locks":9,"cumulative_locks":6605},{"day":"2020-10-21","locks":5,"cumulative_locks":6610},{"day":"2020-10-22","locks":5,"cumulative_locks":6615},{"day":"2020-10-23","locks":4,"cumulative_locks":6619},{"day":"2020-10-24","locks":11,"cumulative_locks":6630},{"day":"2020-10-25","locks":12,"cumulative_locks":6642},{"day":"2020-10-26","locks":10,"cumulative_locks":6652}]